tqdm_joblib/__init__.py
tqdm_joblib-0.0.4.dist-info/METADATA
tqdm_joblib-0.0.4.dist-info/WHEEL
tqdm_joblib-0.0.4.dist-info/top_level.txt
tqdm_joblib-0.0.4.dist-info/RECORD
